powercli/__init__.py
powercli/_help_utils.py
powercli/_style.py
powercli/args.py
powercli/category.py
powercli/command.py
powercli/common.py
powercli/dependency.py
powercli/deprecation.py
powercli/exceptions.py
powercli/methods.py
powercli/parser.py
powercli/py.typed
powercli/static.py
powercli/typedefs.py
powercli/utils.py
powerdoc/__init__.py
powerdoc/__main__.py
powerdoc/builder.py
powerdoc/cli.py
powerdoc/man.py
powerdoc/markdown.py
powerdoc/py.typed
powercli_python-0.2.0.dist-info/LICENSE.txt
powercli_python-0.2.0.dist-info/METADATA
powercli_python-0.2.0.dist-info/WHEEL
powercli_python-0.2.0.dist-info/entry_points.txt
powercli_python-0.2.0.dist-info/RECORD
