Metadata-Version: 2.3
Name: powercli-python
Version: 0.2.0
Summary: Build powerful command-line applications in Python
License: GPLv3
Keywords: cli,command-line
Author: Jonas da Silva
Requires-Python: >=3.13
Classifier: Intended Audience :: Developers
Classifier: License :: OSI Approved :: GNU General Public License v3 (GPLv3)
Classifier: Natural Language :: English
Classifier: Programming Language :: Python
Classifier: Programming Language :: Python :: 3
Classifier: Programming Language :: Python :: 3 :: Only
Classifier: Programming Language :: Python :: 3.12
Classifier: Programming Language :: Python :: 3.13
Classifier: Topic :: Terminals
Classifier: Topic :: Utilities
Classifier: Typing :: Typed
Provides-Extra: dev
Provides-Extra: docs
Requires-Dist: Sphinx (>=8.1.3,<8.2.0) ; extra == "docs"
Requires-Dist: adorable2 (>=0.1.0,<0.2.0)
Requires-Dist: astroid (>=3.3.8,<3.4.0) ; extra == "docs"
Requires-Dist: attrs (>=23.1.0)
Requires-Dist: codespell (>=2.4.1) ; extra == "dev"
Requires-Dist: coverage (>=7.6.12) ; extra == "dev"
Requires-Dist: docstr-coverage (>=2.3.2) ; extra == "dev"
Requires-Dist: furo (>=2024.8.6,<2024.9.0) ; extra == "docs"
Requires-Dist: isort (>=6.0.0) ; extra == "dev"
Requires-Dist: loguru (>=0.7.2)
Requires-Dist: mypy (>=1.15.0) ; extra == "dev"
Requires-Dist: myst-parser (>=4.0.1,<4.1.0) ; extra == "docs"
Requires-Dist: nox (==2025.2.9) ; extra == "dev"
Requires-Dist: pytest (>=7.4.3,<7.5.0) ; extra == "dev"
Requires-Dist: rich (>=13.7.0,<13.8.0) ; extra == "dev"
Requires-Dist: ruff (>=0.9.6) ; extra == "dev"
Requires-Dist: sphinx-autodoc2 (>=0.5.0,<0.6.0) ; extra == "docs"
Requires-Dist: sphinx-inline-tabs ; extra == "docs"
Requires-Dist: wraptext (==1.0.1)
Project-URL: Bug Tracker, https://github.com/phoenixr-codes/powercli/issues
Project-URL: Documentation, https://phoenixr-codes.github.io/powercli
Project-URL: Repository, https://github.com/phoenixr-codes/powercli
